README
setup.cfg
setup.py
pylogix/__init__.py
pylogix/eip.py
pylogix/lgxDevice.py
pylogix2.egg-info/PKG-INFO
pylogix2.egg-info/SOURCES.txt
pylogix2.egg-info/dependency_links.txt
pylogix2.egg-info/top_level.txt