Metadata-Version: 2.1
Name: pylogix2
Version: 0.5.3
Summary: Read/Write Rockwell Automation Logix based PLCs
Home-page: https://github.com/daniel-leicht/pylogix2
Author: Daniel Leicht
Author-email: daniel.leicht@gmail.com
License: Apache License 2.0
Platform: UNKNOWN
Classifier: Programming Language :: Python :: 2.7
Classifier: Programming Language :: Python :: 3.6
Classifier: License :: OSI Approved :: Apache Software License
Classifier: Operating System :: OS Independent
